.bumpversion.cfg
CONTRIBUTING.md
LICENSE
MANIFEST.in
Makefile
README.md
pyproject.toml
setup.py
docs/Makefile
docs/conf.py
docs/index.md
docs/make.bat
docs/img/demo.gif
docs/source/forecast_weather.rst
forecast_weather/__init__.py
forecast_weather/__main__.py
forecast_weather/_version.py
forecast_weather/weather.py
forecast_weather.egg-info/PKG-INFO
forecast_weather.egg-info/SOURCES.txt
forecast_weather.egg-info/dependency_links.txt
forecast_weather.egg-info/requires.txt
forecast_weather.egg-info/top_level.txt
forecast_weather/tests/test_all.py