Metadata-Version: 2.1
Name: forecast-weather
Version: 0.1.2
Summary: This python library easily obtains weather data across various locations and dates.
Author-email: Eugene Kim <ek3192@columbia.edu>
License:                                  Apache License
Project-URL: repository, https://github.com/e7kim/forecast-weather
Classifier: Development Status :: 2 - Pre-Alpha
Classifier: Programming Language :: Python :: Implementation :: CPython
Classifier: Programming Language :: Python :: Implementation :: PyPy
Classifier: Programming Language :: Python :: 3
Classifier: Programming Language :: Python :: 3.7
Classifier: Programming Language :: Python :: 3.8
Classifier: Programming Language :: Python :: 3.9
Classifier: Programming Language :: Python :: 3.10
Classifier: Programming Language :: Python :: 3.11
Requires-Python: >=3.7
Provides-Extra: develop
License-File: LICENSE
